phenobert/__init__.py
phenobert/data/NUM.txt
phenobert/data/hpo.json
phenobert/data/hpo.obo
phenobert/data/stopwords.txt
phenobert/data/68_clinical/ann/09DG00835
phenobert/data/68_clinical/ann/10DG0720
phenobert/data/68_clinical/ann/10DG0840
phenobert/data/68_clinical/ann/11DG1842
phenobert/data/68_clinical/ann/12DG1370
phenobert/data/68_clinical/ann/12DG2311
phenobert/data/68_clinical/ann/13DG0911
phenobert/data/68_clinical/ann/13DG1202
phenobert/data/68_clinical/ann/13DG1545
phenobert/data/68_clinical/ann/13DG1665
phenobert/data/68_clinical/ann/14DG0056
phenobert/data/68_clinical/ann/14DG0467
phenobert/data/68_clinical/ann/14DG0647
phenobert/data/68_clinical/ann/14DG0959
phenobert/data/68_clinical/ann/14DG1188
phenobert/data/68_clinical/ann/14DG1320
phenobert/data/68_clinical/ann/14DG1743
phenobert/data/68_clinical/ann/14DG2158
phenobert/data/68_clinical/ann/15DG0115
phenobert/data/68_clinical/ann/15DG0298
phenobert/data/68_clinical/ann/15DG0299
phenobert/data/68_clinical/ann/15DG0305
phenobert/data/68_clinical/ann/15DG0307
phenobert/data/68_clinical/ann/15DG0315
phenobert/data/68_clinical/ann/15DG0633
phenobert/data/68_clinical/ann/15DG0749
phenobert/data/68_clinical/ann/15DG0837
phenobert/data/68_clinical/ann/15DG2032
phenobert/data/68_clinical/ann/15DG2064
phenobert/data/68_clinical/ann/15DG2206
phenobert/data/68_clinical/ann/15DG2307
phenobert/data/68_clinical/ann/15DG2336
phenobert/data/68_clinical/ann/15DG2492
phenobert/data/68_clinical/ann/15DG2661
phenobert/data/68_clinical/ann/16DG0051
phenobert/data/68_clinical/ann/16DG0105
phenobert/data/68_clinical/ann/16DG0201
phenobert/data/68_clinical/ann/16DG0325
phenobert/data/68_clinical/ann/16DG0402
phenobert/data/68_clinical/ann/16DG0485
phenobert/data/68_clinical/ann/16DG0697
phenobert/data/68_clinical/ann/16DG0971
phenobert/data/68_clinical/ann/16DG1123
phenobert/data/68_clinical/ann/16DG1608
phenobert/data/68_clinical/ann/16DG1625
phenobert/data/68_clinical/ann/17DG0762
phenobert-1.0.5.dist-info/LICENSE
phenobert-1.0.5.dist-info/METADATA
phenobert-1.0.5.dist-info/WHEEL
phenobert-1.0.5.dist-info/top_level.txt
phenobert-1.0.5.dist-info/RECORD
