Metadata-Version: 2.1
Name: phenobert
Version: 1.0.5
Summary: A novel tool for human clinical disease phenotype recognizing with deep learning.
Home-page: https://github.com/EclipseCN/PhenoBERT
Author: NeoFengyh
Author-email: 18210700100@fudan.edu.cn
License: UNKNOWN
Keywords: deep-learning,nlp,bert
Platform: UNKNOWN
Classifier: Development Status :: 4 - Beta
Classifier: Intended Audience :: Developers
Classifier: License :: OSI Approved :: MIT License
Classifier: Programming Language :: Python
Classifier: Programming Language :: Python :: 3
Requires-Python: >=3.6, <4
Requires-Dist: nltk (>=3.5)
Requires-Dist: prettytable (>=1.0.1)
Requires-Dist: fasttext (>=0.9.2)
Requires-Dist: torch (>=1.3.1)
Requires-Dist: scipy (>=1.5.2)
Requires-Dist: stanza (>=1.1.1)
